rtc_tools-2.7.3.dist-info/licenses/COPYING.LESSER
rtctools/__init__.py
rtctools/_version.py
rtctools/rtctoolsapp.py
rtctools/util.py
rtctools/_internal/__init__.py
rtctools/_internal/alias_tools.py
rtctools/_internal/caching.py
rtctools/_internal/casadi_helpers.py
rtctools/_internal/debug_check_helpers.py
rtctools/data/__init__.py
rtctools/data/csv.py
rtctools/data/netcdf.py
rtctools/data/pi.py
rtctools/data/rtc.py
rtctools/data/storage.py
rtctools/data/interpolation/__init__.py
rtctools/data/interpolation/bspline.py
rtctools/data/interpolation/bspline1d.py
rtctools/data/interpolation/bspline2d.py
rtctools/optimization/__init__.py
rtctools/optimization/collocated_integrated_optimization_problem.py
rtctools/optimization/control_tree_mixin.py
rtctools/optimization/csv_lookup_table_mixin.py
rtctools/optimization/csv_mixin.py
rtctools/optimization/goal_programming_mixin.py
rtctools/optimization/goal_programming_mixin_base.py
rtctools/optimization/homotopy_mixin.py
rtctools/optimization/initial_state_estimation_mixin.py
rtctools/optimization/io_mixin.py
rtctools/optimization/linearization_mixin.py
rtctools/optimization/linearized_order_goal_programming_mixin.py
rtctools/optimization/min_abs_goal_programming_mixin.py
rtctools/optimization/modelica_mixin.py
rtctools/optimization/netcdf_mixin.py
rtctools/optimization/optimization_problem.py
rtctools/optimization/pi_mixin.py
rtctools/optimization/planning_mixin.py
rtctools/optimization/single_pass_goal_programming_mixin.py
rtctools/optimization/timeseries.py
rtctools/simulation/__init__.py
rtctools/simulation/csv_mixin.py
rtctools/simulation/io_mixin.py
rtctools/simulation/pi_mixin.py
rtctools/simulation/simulation_problem.py
rtc_tools-2.7.3.dist-info/METADATA
rtc_tools-2.7.3.dist-info/WHEEL
rtc_tools-2.7.3.dist-info/entry_points.txt
rtc_tools-2.7.3.dist-info/top_level.txt
rtc_tools-2.7.3.dist-info/RECORD
