Metadata-Version: 2.4
Name: rtc-tools
Version: 2.7.3
Summary: Toolbox for control and optimization of water systems.
Home-page: https://oss.deltares.nl/web/rtc-tools/home
Download-URL: http://github.com/deltares/rtc-tools/
Author: Deltares
Maintainer: Deltares
Platform: Windows
Platform: Linux
Platform: Mac OS-X
Platform: Unix
Classifier: Development Status :: 4 - Beta
Classifier: Intended Audience :: Science/Research
Classifier: Intended Audience :: Information Technology
Classifier: License :: OSI Approved :: GNU Lesser General Public License v3 (LGPLv3)
Classifier: Programming Language :: Python
Classifier: Programming Language :: Python :: 3
Classifier: Topic :: Scientific/Engineering :: GIS
Classifier: Topic :: Scientific/Engineering :: Mathematics
Classifier: Topic :: Scientific/Engineering :: Physics
Classifier: Operating System :: Microsoft :: Windows
Classifier: Operating System :: POSIX
Classifier: Operating System :: Unix
Classifier: Operating System :: MacOS
Requires-Python: >=3.9
License-File: COPYING.LESSER
Requires-Dist: casadi!=3.6.6,<3.8,>=3.6.3
Requires-Dist: numpy>=1.16.0
Requires-Dist: scipy>=1.0.0
Requires-Dist: pymoca==0.9.*,>=0.9.1
Requires-Dist: rtc-tools-channel-flow>=1.2.0
Requires-Dist: defusedxml>=0.7.0
Requires-Dist: importlib_metadata>=5.0.0; python_version < "3.10"
Provides-Extra: netcdf
Requires-Dist: netCDF4; extra == "netcdf"
Provides-Extra: all
Requires-Dist: netCDF4; extra == "all"
Dynamic: author
Dynamic: classifier
Dynamic: description
Dynamic: download-url
Dynamic: home-page
Dynamic: license-file
Dynamic: maintainer
Dynamic: platform
Dynamic: provides-extra
Dynamic: requires-dist
Dynamic: requires-python
Dynamic: summary
